LICENSE.txt
README.md
setup.cfg
setup.py
airflow_customs_by_novigi.egg-info/PKG-INFO
airflow_customs_by_novigi.egg-info/SOURCES.txt
airflow_customs_by_novigi.egg-info/dependency_links.txt
airflow_customs_by_novigi.egg-info/requires.txt
airflow_customs_by_novigi.egg-info/top_level.txt
airflow_customs_by_novigi/custom_plugings/custom_plugin.py
airflow_customs_by_novigi/hooks/datalake_s3_hook.py
airflow_customs_by_novigi/hooks/odbc_hook.py
airflow_customs_by_novigi/hooks/postgres_hook.py
airflow_customs_by_novigi/hooks/sample_custom_hook.py
airflow_customs_by_novigi/operators/custom_csv_to_s3_opertor.py
airflow_customs_by_novigi/operators/custom_file_load_operator.py
airflow_customs_by_novigi/operators/mssql_to_s3_generic_operator.py
airflow_customs_by_novigi/operators/mssql_to_s3_operator.py
airflow_customs_by_novigi/operators/novigi_csv_to_db.py
airflow_customs_by_novigi/operators/novigi_excel_to_csv.py
airflow_customs_by_novigi/operators/novigi_json_to_csv.py
airflow_customs_by_novigi/operators/novigi_xls_to_csv_operator.py
airflow_customs_by_novigi/operators/s3_to_redshift_staging_copy_operator.py